jimg_ncd/__init__.py
jimg_ncd/config.py
jimg_ncd/nuclei.py
jimg_ncd/utils.py
jimg_ncd-0.1.1.dist-info/licenses/license.txt
jimg_ncd-0.1.1.dist-info/METADATA
jimg_ncd-0.1.1.dist-info/WHEEL
jimg_ncd-0.1.1.dist-info/RECORD
