Metadata-Version: 2.4
Name: jimg_ncd
Version: 0.1.1
Summary: 
License-File: license.txt
Author: Jakub Kubis - JBS
Author-email: jbiosystem@gmail.com
Requires-Python: >=3.12,<3.13
Classifier: Programming Language :: Python :: 3
Classifier: Programming Language :: Python :: 3.12
Requires-Dist: IPython
Requires-Dist: csbdeep
Requires-Dist: gdown (>=5.2.0,<6.0.0)
Requires-Dist: harmonypy (>=0.0.10,<0.0.11)
Requires-Dist: joblib
Requires-Dist: kaleido (==0.2.1)
Requires-Dist: matplotlib (<3.10.0)
Requires-Dist: matplotlib-venn (>=1.1.2,<2.0.0)
Requires-Dist: mpld3
Requires-Dist: nbformat (>=5.10.4,<6.0.0)
Requires-Dist: numpy (==1.26.0)
Requires-Dist: opencv-python
Requires-Dist: openpyxl (>=3.1.5,<4.0.0)
Requires-Dist: pandas
Requires-Dist: pingouin
Requires-Dist: plotly
Requires-Dist: scikit-image
Requires-Dist: scikit-learn (<1.6.0)
Requires-Dist: scipy
Requires-Dist: setuptools (>=80.9.0,<81.0.0)
Requires-Dist: stardist
Requires-Dist: tensorflow (>=2.20.0,<3.0.0)
Requires-Dist: tqdm
Requires-Dist: umap-learn (>=0.5.7,<0.6.0)
